sinapsis_anthropic/src/sinapsis_anthropic/helpers/__init__.py
sinapsis_anthropic/src/sinapsis_anthropic/helpers/anthropic_keys.py
sinapsis_anthropic/src/sinapsis_anthropic/helpers/env_var_keys.py
sinapsis_anthropic/src/sinapsis_anthropic/helpers/mcp_tool_helper.py
sinapsis_anthropic/src/sinapsis_anthropic/templates/__init__.py
sinapsis_anthropic/src/sinapsis_anthropic/templates/anthropic_mcp.py
sinapsis_anthropic/src/sinapsis_anthropic/templates/anthropic_multimodal.py
sinapsis_anthropic/src/sinapsis_anthropic/templates/anthropic_text_generation.py
sinapsis_chat_history/src/sinapsis_chat_history/__init__.py
sinapsis_chat_history/src/sinapsis_chat_history/helpers/__init__.py
sinapsis_chat_history/src/sinapsis_chat_history/helpers/base_provider.py
sinapsis_chat_history/src/sinapsis_chat_history/helpers/database_env_var_keys.py
sinapsis_chat_history/src/sinapsis_chat_history/helpers/factory.py
sinapsis_chat_history/src/sinapsis_chat_history/helpers/postgres_provider.py
sinapsis_chat_history/src/sinapsis_chat_history/templates/__init__.py
sinapsis_chat_history/src/sinapsis_chat_history/templates/chat_history_base.py
sinapsis_chat_history/src/sinapsis_chat_history/templates/chat_history_fetcher.py
sinapsis_chat_history/src/sinapsis_chat_history/templates/chat_history_remover.py
sinapsis_chat_history/src/sinapsis_chat_history/templates/chat_history_reset.py
sinapsis_chat_history/src/sinapsis_chat_history/templates/chat_history_saver.py
sinapsis_chatbots-0.5.11.dist-info/licenses/LICENSE
sinapsis_chatbots_base/src/__init__.py
sinapsis_chatbots_base/src/sinapsis_chatbots_base/__init__.py
sinapsis_chatbots_base/src/sinapsis_chatbots_base/helpers/__init__.py
sinapsis_chatbots_base/src/sinapsis_chatbots_base/helpers/huggingface_access_keys.py
sinapsis_chatbots_base/src/sinapsis_chatbots_base/helpers/llm_keys.py
sinapsis_chatbots_base/src/sinapsis_chatbots_base/helpers/postprocess_text.py
sinapsis_chatbots_base/src/sinapsis_chatbots_base/helpers/tags.py
sinapsis_chatbots_base/src/sinapsis_chatbots_base/templates/__init__.py
sinapsis_chatbots-0.5.11.dist-info/METADATA
sinapsis_chatbots-0.5.11.dist-info/WHEEL
sinapsis_chatbots-0.5.11.dist-info/top_level.txt
sinapsis_chatbots-0.5.11.dist-info/RECORD
