Metadata-Version: 2.4
Name: sinapsis-chatbots
Version: 0.5.11
Summary: Mono repo with packages for text completion tasks
Author-email: SinapsisAI <dev@sinapsis.tech>
Project-URL: Homepage, https://sinapsis.tech
Project-URL: Documentation, https://docs.sinapsis.tech/docs
Project-URL: Tutorials, https://docs.sinapsis.tech/tutorials
Project-URL: Repository, https://github.com/Sinapsis-AI/sinapsis-chatbots.git
Requires-Python: >=3.10
License-File: LICENSE
Requires-Dist: sinapsis>=0.1.1
Provides-Extra: gradio-app
Requires-Dist: sinapsis[webapp]>=0.2.2; extra == "gradio-app"
Provides-Extra: all
Requires-Dist: sinapsis-anthropic[all]; extra == "all"
Requires-Dist: sinapsis-chat-history[all]; extra == "all"
Requires-Dist: sinapsis-chatbots[gradio-app]; extra == "all"
Requires-Dist: sinapsis-chatbots-base[all]; extra == "all"
Requires-Dist: sinapsis-llama-cpp[all]; extra == "all"
Requires-Dist: sinapsis-llama-index[all]; extra == "all"
Requires-Dist: sinapsis-mem0[all]; extra == "all"
Provides-Extra: chatbot-app
Requires-Dist: sinapsis[webapp]>=0.2.15; extra == "chatbot-app"
Provides-Extra: chatbot
Requires-Dist: sinapsis-langchain-readers[langchain-pdfs-readers]>=0.1.4; extra == "chatbot"
Requires-Dist: sinapsis-langchain-readers[langchain-wikipedia-readers]>=0.1.4; extra == "chatbot"
Requires-Dist: sinapsis-langchain-readers[langchain-productivity-tools]>=0.1.4; extra == "chatbot"
Requires-Dist: sinapsis-openai>=0.1.9; extra == "chatbot"
Dynamic: license-file
